{
    "availableAccounts": [
        {
            "accountNumber": {
                "bankCode": 600,
                "number": 234987111,
                "prefix": null
            },
            "accountName": "Tom Plus",
            "availableBalance": 37472,
            "directDebitExists": true,
            "isDefault" : false
        },
        {
            "accountNumber": {
                "bankCode": 600,
                "number": 224870199,
                "prefix": null
            },
            "accountName": "Tomík",
            "availableBalance": 15750,
            "directDebitExists": false,
            "isDefault" : true
        },
    ],
    "bankList": [
        {
          "alphaCode": "KOMB",
          "bankCode": 100,
          "bankCodeLabel": "0100",
          "name": "Komerční banka a.s."
        },
        {
          "alphaCode": "CEKO",
          "bankCode": 300,
          "bankCodeLabel": "0300",
          "name": "Československá obch.banka a.s."
        },
        {
          "alphaCode": "AGBA",
          "bankCode": 600,
          "bankCodeLabel": "0600",
          "name": "MONETA Money Bank, a. s."
        },
        {
          "alphaCode": "CNBA",
          "bankCode": 710,
          "bankCodeLabel": "0710",
          "name": "Česká národní banka"
        },
        {
          "alphaCode": "CSPO",
          "bankCode": 800,
          "bankCodeLabel": "0800",
          "name": "Česká spořitelna a.s."
        },
        {
          "alphaCode": "FIOZ",
          "bankCode": 2010,
          "bankCodeLabel": "2010",
          "name": "Fio banka a.s."
        },
        {
          "alphaCode": "BOTK",
          "bankCode": 2020,
          "bankCodeLabel": "2020",
          "name": "Bank of Tokyo-Mitsubishi UFJ"
        },
        {
          "alphaCode": "CITF",
          "bankCode": 2060,
          "bankCodeLabel": "2060",
          "name": "Citfin, spořitelní družstvo"
        },
        {
          "alphaCode": "MPUZ",
          "bankCode": 2070,
          "bankCodeLabel": "2070",
          "name": "Moravsky Penezni Ustav sp.dr."
        },
        {
          "alphaCode": "CMHB",
          "bankCode": 2100,
          "bankCodeLabel": "2100",
          "name": "ČSOB Hypoteční banka a.s."
        },
        {
          "alphaCode": "PDSD",
          "bankCode": 2200,
          "bankCodeLabel": "2200",
          "name": "Peněžní dům,spořitelní družst"
        },
        {
          "alphaCode": "ARTZ",
          "bankCode": 2220,
          "bankCodeLabel": "2220",
          "name": "Artesa, spořitelní družstvo"
        },
        {
          "alphaCode": "CREZ",
          "bankCode": 2250,
          "bankCodeLabel": "2250",
          "name": "Záložna CREDITAS, spor. dr."
        },
        {
          "alphaCode": "ANOS",
          "bankCode": 2260,
          "bankCodeLabel": "2260",
          "name": "ANO spořitelní družstvo"
        },
        {
          "alphaCode": "CITI",
          "bankCode": 2600,
          "bankCodeLabel": "2600",
          "name": "Citibank Europe plc."
        },
        {
          "alphaCode": "CABV",
          "bankCode": 2700,
          "bankCodeLabel": "2700",
          "name": "UniCredit Bank CR and SR,a.s."
        },
        {
          "alphaCode": "BAIR",
          "bankCode": 3030,
          "bankCodeLabel": "3030",
          "name": "Air bank a.s."
        },
        {
          "alphaCode": "BPPF",
          "bankCode": 3050,
          "bankCodeLabel": "3050",
          "name": "BNP Paribas Personal Finance"
        },
        {
          "alphaCode": "BPKO",
          "bankCode": 3060,
          "bankCodeLabel": "3060",
          "name": "PKO BP S.A., Czech Branch"
        },
        {
          "alphaCode": "INGB",
          "bankCode": 3500,
          "bankCodeLabel": "3500",
          "name": "ING Bank N.V."
        },
        {
          "alphaCode": "DRES",
          "bankCode": 4000,
          "bankCodeLabel": "4000",
          "name": "Max banka a.s."
        },
        {
          "alphaCode": "CMZR",
          "bankCode": 4300,
          "bankCodeLabel": "4300",
          "name": "Českomor.zár.a rozv.banka,a.s."
        },
        {
          "alphaCode": "RZBC",
          "bankCode": 5500,
          "bankCodeLabel": "5500",
          "name": "Raiffeisenbank a.s."
        },
        {
          "alphaCode": "JTBP",
          "bankCode": 5800,
          "bankCodeLabel": "5800",
          "name": "J&T Banka, a.s."
        },
        {
          "alphaCode": "PMBA",
          "bankCode": 6000,
          "bankCodeLabel": "6000",
          "name": "PPF banka a.s."
        },
        {
          "alphaCode": "COBA",
          "bankCode": 6200,
          "bankCodeLabel": "6200",
          "name": "COMMERZBANK AG"
        },
        {
          "alphaCode": "BREX",
          "bankCode": 6210,
          "bankCodeLabel": "6210",
          "name": "mBank S.A., organizační složka"
        },
        {
          "alphaCode": "GEBA",
          "bankCode": 6300,
          "bankCodeLabel": "6300",
          "name": "BNP Paribas Fortis SA/NV p.ČR"
        },
        {
          "alphaCode": "PARB",
          "bankCode": 6363,
          "bankCodeLabel": "6363",
          "name": "Partners Banka, a.s."
        },
        {
          "alphaCode": "SUBACA",
          "bankCode": 6700,
          "bankCodeLabel": "6700",
          "name": "Všeobecná úver.banka,pob.Praha"
        },
        {
          "alphaCode": "VBOE",
          "bankCode": 6800,
          "bankCodeLabel": "6800",
          "name": "Sberbank CZ, a.s."
        },
        {
          "alphaCode": "DEUT",
          "bankCode": 7910,
          "bankCodeLabel": "7910",
          "name": "Deutsche Bank A.G.Filiale Prag"
        },
        {
          "alphaCode": "ARSS",
          "bankCode": 7950,
          "bankCodeLabel": "7950",
          "name": "Raiffeisen stav.spořitelna a.s"
        },
        {
          "alphaCode": "CMSS",
          "bankCode": 7960,
          "bankCodeLabel": "7960",
          "name": "ČSOB Stavební spořitelna, a.s."
        },
        {
          "alphaCode": "SSWT",
          "bankCode": 7970,
          "bankCodeLabel": "7970",
          "name": "Wüstenrot-stav. spořitelna a.s"
        },
        {
          "alphaCode": "VSPO",
          "bankCode": 7990,
          "bankCodeLabel": "7990",
          "name": "Modrá pyramida stav.spoř.,a.s."
        },
        {
          "alphaCode": "DRBW",
          "bankCode": 8030,
          "bankCodeLabel": "8030",
          "name": "Raiff.im Stift.Waldsas.eG,Cheb"
        },
        {
          "alphaCode": "SSCS",
          "bankCode": 8060,
          "bankCodeLabel": "8060",
          "name": "Stavební spořitelna Čes.sp.a.s"
        },
        {
          "alphaCode": "CEXB",
          "bankCode": 8090,
          "bankCodeLabel": "8090",
          "name": "Česká exportní banka a.s."
        },
        {
          "alphaCode": "MIDL",
          "bankCode": 8150,
          "bankCodeLabel": "8150",
          "name": "HSBC Continental Europe, CZ"
        },
        {
          "alphaCode": "WELA",
          "bankCode": 8190,
          "bankCodeLabel": "8190",
          "name": "Sparkasse Oberlausitz-Nieders."
        },
        {
          "alphaCode": "BKCH",
          "bankCode": 8250,
          "bankCodeLabel": "8250",
          "name": "Bank of China (Hungary)"
        },
        {
          "alphaCode": "ICBK",
          "bankCode": 8265,
          "bankCodeLabel": "8265",
          "name": "Industr.-Commer. Bank of China"
        },
        {
          "alphaCode": "FEMA",
          "bankCode": 8500,
          "bankCodeLabel": "8500",
          "name": "Multitude Bank p.l.c."
        },
        {
          "alphaCode": "FAK1",
          "bankCode": 9998,
          "bankCodeLabel": "9998",
          "name": "FAKE 1 test banka"
        },
        {
          "alphaCode": "FAKE",
          "bankCode": 9999,
          "bankCodeLabel": "9999",
          "name": "FAKE test banka"
        }
    ],
    "cardData" : {
        "minRepaymentPercent": 6,
        "interestRate": 18.9,
        "interestFreePeriod": null
    }
}
